
[
  {
    "Title": "Black Alumni Weekend: \"OnBoard\" Screening, Panel & Reception",
    "Start Time": "2:30 pm",
    "End Time": "5:30 pm",
    "Date": "April 19",
    "Location": "Rouse & Robertson Halls"
  },
  {
    "Title": "M.S. in Commerce Information Session",
    "Start Time": null,
    "End Time": null,
    "Date": "April 23",
    "Location": null
  },
  {
    "Title": "Alternative Investing in a Rapidly Changing Environment  McIntire Alumni Panel",
    "Start Time": null,
    "End Time": null,
    "Date": "April 25",
    "Location": null
  },
  {
    "Title": "Connaughton Speaker Series: A Founders Conversation",
    "Start Time": null,
    "End Time": null,
    "Date": "April 26",
    "Location": null
  },
  {
    "Title": "NYC Alumni & Friends Reception",
    "Start Time": null,
    "End Time": null,
    "Date": "May 07",
    "Location": null
  },
  {
    "Title": "M.S. in Commerce Information Session",
    "Start Time": null,
    "End Time": null,
    "Date": "May 09",
    "Location": null
  },
  {
    "Title": "Knowledge Continuum",
    "Start Time": null,
    "End Time": null,
    "Date": "May 10",
    "Location": null
  },
  {
    "Title": "M.S. in Accounting Information Session",
    "Start Time": null,
    "End Time": null,
    "Date": "May 14",
    "Location": null
  },
  {
    "Title": "London Pub Night with Carl Zeithaml",
    "Start Time": null,
    "End Time": null,
    "Date": "May 30",
    "Location": null
  },
  {
    "Title": "Reunions Weekend Lunch: Classes of '94, '89, '84, '79, '74, TJ Society",
    "Start Time": null,
    "End Time": null,
    "Date": "June 01",
    "Location": null
  },
  {
    "Title": "Reunions Weekend Lunch: Classes of '19, '14, '09, '04, '99",
    "Start Time": null,
    "End Time": null,
    "Date": "June 08",
    "Location": null
  },
  {
    "Title": "A Conversation on Capitalism & Democracy",
    "Start Time": null,
    "End Time": null,
    "Date": "June 19",
    "Location": null
  },
  {
    "Title": "Information Session M.S. in the Management of IT Application Strategy Session",
    "Start Time": "5:00 pm",
    "End Time": "6:00 pm",
    "Date": "April 18",
    "Location": "Virtual"
  },
  {
    "Title": "Information Session M.S. in Business Analytics Application Strategy Session",
    "Start Time": "5:00 pm",
    "End Time": "6:00 pm",
    "Date": "April 18",
    "Location": "Virtual"
  },
  {
    "Title": "180 Degrees: Bain & Co. Women's Case Competition",
    "Start Time": "5:00 pm",
    "End Time": "9:00 pm",
    "Date": "April 18",
    "Location": "Rouse & Robertson Halls"
  },
  {
    "Title": "Information Session M.S. in Accounting Information Session",
    "Start Time": "7:00 pm",
    "End Time": "8:00 pm",
    "Date": "April 18",
    "Location": "Virtual"
  },
  {
    "Title": "180 Degrees: Bain & Co. Women's Case Competition",
    "Start Time": "8:00 am",
    "End Time": "1:00 pm",
    "Date": "April 19",
    "Location": "Rouse & Robertson Halls"
  },
  {
    "Title": "Commerce Council Weekly Meeting",
    "Start Time": "12:00 pm",
    "End Time": "3:00 pm",
    "Date": "April 19",
    "Location": "Rouse & Robertson Halls"
  },
  {
    "Title": "M.S. in the Management of IT Student Panel",
    "Start Time": "6:00 pm",
    "End Time": "7:00 pm",
    "Date": "April 23",
    "Location": "Virtual"
  },
  {
    "Title": "Blockchain at UVA x EasyA",
    "Start Time": "6:00 pm",
    "End Time": "7:00 pm",
    "Date": "April 23",
    "Location": "Rouse & Robertson Halls"
  }
]
